{
  "simple-colored-folder@@bg-templaterscripts@@light": "#F8F9FB",
  "simple-colored-folder@@bg-templaterscripts@@dark": "#808080",
  "simple-colored-folder@@col-templaterscripts@@light": "#575757",
  "simple-colored-folder@@bg-templates@@light": "#F8F9FB",
  "simple-colored-folder@@col-templates@@light": "#575757",
  "simple-colored-folder@@bg-00sistema@@light": "#E1ECF7",
  "simple-colored-folder@@col-00sistema@@light": "#FFFFFF",
  "simple-colored-folder@@bg-01materie@@light": "#AECBEB",
  "simple-colored-folder@@col-01materie@@light": "#FFFFFF",
  "simple-colored-folder@@bg-02risorse@@light": "#83B0E1",
  "simple-colored-folder@@col-02risorse@@light": "#FFFFFF",
  "simple-colored-folder@@bg-03archivio@@light": "#71A5DE",
  "simple-colored-folder@@col-03archivio@@light": "#FFFFFF",
  "simple-colored-folder@@spf-saturate-hover": 150
}